{
  "generatedAt": "2026-03-09T10:02:43.002Z",
  "version": 1,
  "news": {
    "articles": [],
    "topics": [],
    "stories": [],
    "engagedStories": [],
    "topStories": {
      "indiaRecent": [],
      "indiaEngaged": [],
      "worldRecent": [],
      "worldEngaged": []
    }
  },
  "sentiment": {
    "average": {
      "pos": 0,
      "neu": 0,
      "neg": 0
    },
    "articleCount": 0
  },
  "plots": {
    "sentimentTimeline": [
      {
        "start": "2026-03-09T06:02:43.004Z",
        "end": "2026-03-09T07:02:43.004Z",
        "pos": 0,
        "neu": 0,
        "neg": 0,
        "count": 0
      },
      {
        "start": "2026-03-09T07:02:43.004Z",
        "end": "2026-03-09T08:02:43.004Z",
        "pos": 0,
        "neu": 0,
        "neg": 0,
        "count": 0
      },
      {
        "start": "2026-03-09T08:02:43.004Z",
        "end": "2026-03-09T09:02:43.004Z",
        "pos": 0,
        "neu": 0,
        "neg": 0,
        "count": 0
      },
      {
        "start": "2026-03-09T09:02:43.004Z",
        "end": "2026-03-09T10:02:43.004Z",
        "pos": 0,
        "neu": 0,
        "neg": 0,
        "count": 0
      }
    ]
  },
  "industryLeaderboard": {
    "rows": []
  },
  "meta": {
    "source": "bootstrap-cache",
    "schemaVersion": 1,
    "markets": {
      "quotes": [],
      "updatedAt": 1773050563005
    }
  }
}
